Workbook

Sheet Read me
A1: Silpo 2027 — DK, Resto & Stores P&L calculator
A3: How this workbook works
A5: Inputs: yellow cells are editable. DK/resto is populated from the provided 12-month historical calculator; Stores is populated from SILPO business model (6), scenario “Спільна ставка - 16% ДК + Stores”.
A6: Scenarios: annual total only. Each tier shows H1 and H2 commission, the GMV threshold, CP L1 and CP L2 both in € and % of GMV.
A7: P&L by vertical: displays Dark Kitchen, Resto, Stores and Portfolio separately for every scenario, including eater fees and all cost lines.
A8: DF campaign for DK/resto is historical information inside existing demand incentives and is not deducted twice. Incremental DF campaign is a separate Stores cash investment for 6 of 12 months.
A9: Bolt+ discount uses delivery base only. SF and SOF are excluded from the discount input.

Sheet Inputs
A1: Inputs — historical data and 2027 projection
A3: Yellow cells are editable. 2027 projection = historical 12-month baseline × volume multiplier.
A5: Incremental investments and promotional assumptions
A6: Input | B6: Value | C6: Unit | D6: Treatment
A7: DF campaign · Stores | B7: 28000 | C7: € / year | D7: Cash; activation 6 of 12 months
A8: DF campaign · DK + Resto | B8: 14418.17 | C8: € / year | D8: Historical info only; already included in existing DI
A9: Bolt+ · DK + Resto | B9: 14615.45 | C9: € / year | D9: Cash; delivery base only
A10: Bolt+ · Stores | B10: 10800 | C10: € / year | D10: Cash; delivery base only
A11: Public Launch cash | B11: 10000 | C11: € / year | D11: Cash; allocated by GMV
A12: In-kind marketing | B12: 11200 | C12: € / year | D12: Not deducted from cash P&L; allocated by GMV
A13: Sponsored Listing discount | B13: 0 | C13: € / year | D13: Cash impact; allocated by GMV
A14: Other cash investment | B14: 0 | C14: € / year | D14: Cash impact; allocated by GMV
A17: Historical 12-month base and 2027 projection
A18: Metric | B18: Dark Kitchen | C18: Resto | D18: Stores | E18: Portfolio | F18: Source / treatment
A19: Historical delivered orders | B19: 56959 | C19: 1931 | D19: 50400 | E19: =SUM(B19:D19) -> 109290 | F19: Provided DK/resto calculator
A20: Historical GMV | B20: 1029023.6 | C20: 34036.47 | D20: 852768 | E20: =SUM(B20:D20) -> 1915828 | F20: Provided DK/resto calculator
A21: Historical eater-fee revenue | B21: 115473.31 | C21: 3810.16 | D21: 96768 | E21: =SUM(B21:D21) -> 216051.47 | F21: Provided DK/resto calculator
A22: Historical commission revenue | B22: 207245.02 | C22: 7668.47 | D22: 120960 | E22: =SUM(B22:D22) -> 335873.49 | F22: Provided DK/resto calculator
A23: Historical direct costs before DI | B23: 185586.06 | C23: 6495.05 | D23: 171397.71 | E23: =SUM(B23:D23) -> 363478.82 | F23: Provided DK/resto calculator
A24: Historical CP L1 | B24: 137132.27 | C24: 4983.58 | D24: 46330.286 | E24: =SUM(B24:D24) -> 188446.14 | F24: Provided DK/resto calculator
A25: Historical demand incentives | B25: 99019.71 | C25: 2001.89 | D25: 28728 | E25: =SUM(B25:D25) -> 129749.6 | F25: Provided DK/resto calculator
A26: Historical CP L2 | B26: 38112.56 | C26: 2981.69 | D26: 17602.286 | E26: =SUM(B26:D26) -> 58696.536 | F26: Provided DK/resto calculator
A27: 2027 volume multiplier | B27: 1 | C27: 1 | D27: 1 | E27: =AVERAGE(B27:D27) -> 1 | F27: Historical × volume multiplier
A28: 2027 projected orders | B28: =B19*B27 -> 56959 | C28: =C19*C27 -> 1931 | D28: =D19*D27 -> 50400 | E28: =SUM(B28:D28) -> 109290 | F28: Historical × volume multiplier
A29: 2027 projected GMV | B29: =B20*B27 -> 1029023.6 | C29: =C20*C27 -> 34036.47 | D29: =D20*D27 -> 852768 | E29: =SUM(B29:D29) -> 1915828 | F29: Historical × volume multiplier
A30: 2027 projected eater fees | B30: =B21*B27 -> 115473.31 | C30: =C21*C27 -> 3810.16 | D30: =D21*D27 -> 96768 | E30: =SUM(B30:D30) -> 216051.47 | F30: Historical × volume multiplier
A31: 2027 projected direct costs | B31: =B23*B27 -> 185586.06 | C31: =C23*C27 -> 6495.05 | D31: =D23*D27 -> 171397.71 | E31: =SUM(B31:D31) -> 363478.82 | F31: Historical × volume multiplier
A32: 2027 projected existing DI | B32: =B25*B27 -> 99019.71 | C32: =C25*C27 -> 2001.89 | D32: =D25*D27 -> 28728 | E32: =SUM(B32:D32) -> 129749.6 | F32: Historical × volume multiplier

Sheet Scenarios
A1: Scenarios — annual total, H1/H2 rate schedule and GMV thresholds
A3: Rate cells are yellow and editable. Threshold is a commercial trigger; current Stores average monthly GMV is visible in Inputs / 2027 projected GMV.
A5: Scenario | B5: DK H1 | C5: DK H2 | D5: Resto H1 | E5: Resto H2 | F5: Stores H1 | G5: Stores H2 | H5: GMV threshold / month | I5: Model comment | J5: Orders | K5: GMV | L5: Eater fees | M5: Commission | N5: Direct costs | O5: CP L1 € | P5: CP L1 % | Q5: Existing DI | R5: Historical DF DK/resto inside DI | S5: CP L2 € | T5: CP L2 % | U5: DF Stores | V5: Bolt+ | W5: PL cash | X5: Final CP L2 | Y5: Final % | Z5: In-kind | AA5: Partner saving
A6: Current effective rates | B6: 0.20139968 | C6: 0.20139968 | D6: 0.22530157 | E6: 0.22530157 | F6: 0.16 | G6: 0.16 | H6: 0 | I6: Current historical / Shared16 stores | J6: =SUM(Inputs!$B$28:$D$28) -> 109290 | K6: =SUM(Inputs!$B$29:$D$29) -> 1915828 | L6: =SUM(Inputs!$B$30:$D$30) -> 216051.47 | M6: =Inputs!$B$29*(B6+C6)/2+Inputs!$C$29*(D6+E6)/2+Inputs!$D$29*(F6+G6)/2 -> 351356.37 | N6: =SUM(Inputs!$B$31:$D$31) -> 363478.82 | O6: =M6-N6+L6 -> 203929.02 | P6: =O6/K6 -> 0.10644432 | Q6: =SUM(Inputs!$B$32:$D$32) -> 129749.6 | R6: =Inputs!$B$8 -> 14418.17 | S6: =O6-Q6 -> 74179.416 | T6: =S6/K6 -> 0.038719246 | U6: =Inputs!$B$7 -> 28000 | V6: =Inputs!$B$9+Inputs!$B$10 -> 25415.45 | W6: =Inputs!$B$11 -> 10000 | X6: =S6-SUM(U6:W6) -> 10763.966 | Y6: =X6/K6 -> 0.0056184408 | Z6: =Inputs!$B$12 -> 11200 | AA6: =$M$6-M6 -> -15482.88
A7: Tier 1 · launch | B7: 0.25 | C7: 0.25 | D7: 0.25 | E7: 0.25 | F7: 0.12 | G7: 0.12 | H7: 0 | I7: 12 months at launch rates | J7: =SUM(Inputs!$B$28:$D$28) -> 109290 | K7: =SUM(Inputs!$B$29:$D$29) -> 1915828 | L7: =SUM(Inputs!$B$30:$D$30) -> 216051.47 | M7: =Inputs!$B$29*(B7+C7)/2+Inputs!$C$29*(D7+E7)/2+Inputs!$D$29*(F7+G7)/2 -> 368097.17 | N7: =SUM(Inputs!$B$31:$D$31) -> 363478.82 | O7: =M7-N7+L7 -> 220669.82 | P7: =O7/K7 -> 0.11518248 | Q7: =SUM(Inputs!$B$32:$D$32) -> 129749.6 | R7: =Inputs!$B$8 -> 14418.17 | S7: =O7-Q7 -> 90920.216 | T7: =S7/K7 -> 0.047457399 | U7: =Inputs!$B$7 -> 28000 | V7: =Inputs!$B$9+Inputs!$B$10 -> 25415.45 | W7: =Inputs!$B$11 -> 10000 | X7: =S7-SUM(U7:W7) -> 27504.766 | Y7: =X7/K7 -> 0.014356595 | Z7: =Inputs!$B$12 -> 11200 | AA7: =$M$6-M7 -> -32223.68
A8: Tier 2 · €33k stores GMV / month | B8: 0.25 | C8: 0.2 | D8: 0.25 | E8: 0.2 | F8: 0.12 | G8: 0.12 | H8: 33000 | I8: 6m DK/resto 25%, then 6m 20%; threshold €33k | J8: =SUM(Inputs!$B$28:$D$28) -> 109290 | K8: =SUM(Inputs!$B$29:$D$29) -> 1915828 | L8: =SUM(Inputs!$B$30:$D$30) -> 216051.47 | M8: =Inputs!$B$29*(B8+C8)/2+Inputs!$C$29*(D8+E8)/2+Inputs!$D$29*(F8+G8)/2 -> 341520.67 | N8: =SUM(Inputs!$B$31:$D$31) -> 363478.82 | O8: =M8-N8+L8 -> 194093.32 | P8: =O8/K8 -> 0.10131041 | Q8: =SUM(Inputs!$B$32:$D$32) -> 129749.6 | R8: =Inputs!$B$8 -> 14418.17 | S8: =O8-Q8 -> 64343.715 | T8: =S8/K8 -> 0.033585329 | U8: =Inputs!$B$7 -> 28000 | V8: =Inputs!$B$9+Inputs!$B$10 -> 25415.45 | W8: =Inputs!$B$11 -> 10000 | X8: =S8-SUM(U8:W8) -> 928.26544 | Y8: =X8/K8 -> 0.0004845244 | Z8: =Inputs!$B$12 -> 11200 | AA8: =$M$6-M8 -> -5647.179
A9: Tier 3a · step-down to 16% | B9: 0.2 | C9: 0.16 | D9: 0.2 | E9: 0.16 | F9: 0.12 | G9: 0.12 | H9: 65000 | I9: 6m DK/resto 20%, then 6m 16%; stores stays 12% | J9: =SUM(Inputs!$B$28:$D$28) -> 109290 | K9: =SUM(Inputs!$B$29:$D$29) -> 1915828 | L9: =SUM(Inputs!$B$30:$D$30) -> 216051.47 | M9: =Inputs!$B$29*(B9+C9)/2+Inputs!$C$29*(D9+E9)/2+Inputs!$D$29*(F9+G9)/2 -> 293682.97 | N9: =SUM(Inputs!$B$31:$D$31) -> 363478.82 | O9: =M9-N9+L9 -> 146255.61 | P9: =O9/K9 -> 0.076340679 | Q9: =SUM(Inputs!$B$32:$D$32) -> 129749.6 | R9: =Inputs!$B$8 -> 14418.17 | S9: =O9-Q9 -> 16506.014 | T9: =S9/K9 -> 0.0086156029 | U9: =Inputs!$B$7 -> 28000 | V9: =Inputs!$B$9+Inputs!$B$10 -> 25415.45 | W9: =Inputs!$B$11 -> 10000 | X9: =S9-SUM(U9:W9) -> -46909.436 | Y9: =X9/K9 -> -0.024485202 | Z9: =Inputs!$B$12 -> 11200 | AA9: =$M$6-M9 -> 42190.523
A10: Tier 3a · 12m DK/resto 16% | B10: 0.16 | C10: 0.16 | D10: 0.16 | E10: 0.16 | F10: 0.12 | G10: 0.12 | H10: 65000 | I10: 12 months: stores 12%, DK/resto 16% | J10: =SUM(Inputs!$B$28:$D$28) -> 109290 | K10: =SUM(Inputs!$B$29:$D$29) -> 1915828 | L10: =SUM(Inputs!$B$30:$D$30) -> 216051.47 | M10: =Inputs!$B$29*(B10+C10)/2+Inputs!$C$29*(D10+E10)/2+Inputs!$D$29*(F10+G10)/2 -> 272421.77 | N10: =SUM(Inputs!$B$31:$D$31) -> 363478.82 | O10: =M10-N10+L10 -> 124994.41 | P10: =O10/K10 -> 0.065243023 | Q10: =SUM(Inputs!$B$32:$D$32) -> 129749.6 | R10: =Inputs!$B$8 -> 14418.17 | S10: =O10-Q10 -> -4755.1872 | T10: =S10/K10 -> -0.0024820532 | U10: =Inputs!$B$7 -> 28000 | V10: =Inputs!$B$9+Inputs!$B$10 -> 25415.45 | W10: =Inputs!$B$11 -> 10000 | X10: =S10-SUM(U10:W10) -> -68170.637 | Y10: =X10/K10 -> -0.035582858 | Z10: =Inputs!$B$12 -> 11200 | AA10: =$M$6-M10 -> 63451.724
A11: Tier 3b · step to shared 16% | B11: 0.2 | C11: 0.16 | D11: 0.2 | E11: 0.16 | F11: 0.12 | G11: 0.16 | H11: 65000 | I11: 6m tier 2, then 6m shared 16% | J11: =SUM(Inputs!$B$28:$D$28) -> 109290 | K11: =SUM(Inputs!$B$29:$D$29) -> 1915828 | L11: =SUM(Inputs!$B$30:$D$30) -> 216051.47 | M11: =Inputs!$B$29*(B11+C11)/2+Inputs!$C$29*(D11+E11)/2+Inputs!$D$29*(F11+G11)/2 -> 310738.33 | N11: =SUM(Inputs!$B$31:$D$31) -> 363478.82 | O11: =M11-N11+L11 -> 163310.97 | P11: =O11/K11 -> 0.085243023 | Q11: =SUM(Inputs!$B$32:$D$32) -> 129749.6 | R11: =Inputs!$B$8 -> 14418.17 | S11: =O11-Q11 -> 33561.374 | T11: =S11/K11 -> 0.017517947 | U11: =Inputs!$B$7 -> 28000 | V11: =Inputs!$B$9+Inputs!$B$10 -> 25415.45 | W11: =Inputs!$B$11 -> 10000 | X11: =S11-SUM(U11:W11) -> -29854.076 | Y11: =X11/K11 -> -0.015582858 | Z11: =Inputs!$B$12 -> 11200 | AA11: =$M$6-M11 -> 25135.163
A12: Tier 3b · 12m shared 16% | B12: 0.16 | C12: 0.16 | D12: 0.16 | E12: 0.16 | F12: 0.16 | G12: 0.16 | H12: 65000 | I12: 12 months shared 16% | J12: =SUM(Inputs!$B$28:$D$28) -> 109290 | K12: =SUM(Inputs!$B$29:$D$29) -> 1915828 | L12: =SUM(Inputs!$B$30:$D$30) -> 216051.47 | M12: =Inputs!$B$29*(B12+C12)/2+Inputs!$C$29*(D12+E12)/2+Inputs!$D$29*(F12+G12)/2 -> 306532.49 | N12: =SUM(Inputs!$B$31:$D$31) -> 363478.82 | O12: =M12-N12+L12 -> 159105.13 | P12: =O12/K12 -> 0.083047711 | Q12: =SUM(Inputs!$B$32:$D$32) -> 129749.6 | R12: =Inputs!$B$8 -> 14418.17 | S12: =O12-Q12 -> 29355.533 | T12: =S12/K12 -> 0.015322635 | U12: =Inputs!$B$7 -> 28000 | V12: =Inputs!$B$9+Inputs!$B$10 -> 25415.45 | W12: =Inputs!$B$11 -> 10000 | X12: =S12-SUM(U12:W12) -> -34059.917 | Y12: =X12/K12 -> -0.01777817 | Z12: =Inputs!$B$12 -> 11200 | AA12: =$M$6-M12 -> 29341.004

Sheet P&L by vertical
A1: P&L by vertical — all annual scenarios
A3: Each row has an internal formula and a cached opening value. Eater fees are shown separately but already included in historical unit economics; they are not added twice.
A5: Scenario | B5: Vertical | C5: Orders | D5: GMV | E5: AOV | F5: Eater fees | G5: H1 rate | H5: H2 rate | I5: Commission | J5: Direct costs | K5: CP L1 € | L5: CP L1 % | M5: Existing DI | N5: Historical DF inside DI | O5: CP L2 € | P5: CP L2 % | Q5: DF Stores | R5: Bolt+ | S5: PL cash | T5: Final CP L2 | U5: Final %
A6: Current effective rates | B6: DK | C6: =Inputs!$B$28 -> 56959 | D6: =Inputs!$B$29 -> 1029023.6 | E6: =D6/C6 -> 18.06604 | F6: =Inputs!$B$30 -> 115473.31 | G6: =Scenarios!$B$6 -> 0.20139968 | H6: =Scenarios!$C$6 -> 0.20139968 | I6: =D6*(G6+H6)/2 -> 207245.02 | J6: =Inputs!$B$31 -> 185586.06 | K6: =I6+F6-J6 -> 137132.27 | L6: =K6/D6 -> 0.13326446 | M6: =Inputs!$B$32 -> 99019.71 | N6: =Inputs!$B$8*D6/(Inputs!$B$29+Inputs!$C$29) -> 14297.19 | O6: =K6-M6 -> 38112.56 | P6: =O6/D6 -> 0.037037597 | Q6: =0 -> 0 | R6: =Inputs!$B$9*D6/(Inputs!$B$29+Inputs!$C$29) -> 14147.501 | S6: =Inputs!$B$11*D6/SUM(Inputs!$B$29:$D$29) -> 5371.1688 | T6: =O6-Q6-R6-S6 -> 18593.891 | U6: =T6/D6 -> 0.018069451
A7: Current effective rates | B7: Resto | C7: =Inputs!$C$28 -> 1931 | D7: =Inputs!$C$29 -> 34036.47 | E7: =D7/C7 -> 17.626344 | F7: =Inputs!$C$30 -> 3810.16 | G7: =Scenarios!$D$6 -> 0.22530157 | H7: =Scenarios!$E$6 -> 0.22530157 | I7: =D7*(G7+H7)/2 -> 7668.47 | J7: =Inputs!$C$31 -> 6495.05 | K7: =I7+F7-J7 -> 4983.58 | L7: =K7/D7 -> 0.14641883 | M7: =Inputs!$C$32 -> 2001.89 | N7: =Inputs!$B$8*D7/(Inputs!$B$29+Inputs!$C$29) -> 120.98 | O7: =K7-M7 -> 2981.69 | P7: =O7/D7 -> 0.087602798 | Q7: =0 -> 0 | R7: =Inputs!$B$9*D7/(Inputs!$B$29+Inputs!$C$29) -> 467.94942 | S7: =Inputs!$B$11*D7/SUM(Inputs!$B$29:$D$29) -> 177.65932 | T7: =O7-Q7-R7-S7 -> 2336.0813 | U7: =T7/D7 -> 0.068634652
A8: Current effective rates | B8: Stores | C8: =Inputs!$D$28 -> 50400 | D8: =Inputs!$D$29 -> 852768 | E8: =D8/C8 -> 16.92 | F8: =Inputs!$D$30 -> 96768 | G8: =Scenarios!$F$6 -> 0.16 | H8: =Scenarios!$G$6 -> 0.16 | I8: =D8*(G8+H8)/2 -> 136442.88 | J8: =Inputs!$D$31 -> 171397.71 | K8: =I8+F8-J8 -> 61813.166 | L8: =K8/D8 -> 0.072485326 | M8: =Inputs!$D$32 -> 28728 | N8: =0 -> 0 | O8: =K8-M8 -> 33085.166 | P8: =O8/D8 -> 0.038797383 | Q8: =Inputs!$B$7 -> 28000 | R8: =Inputs!$B$10 -> 10800 | S8: =Inputs!$B$11*D8/SUM(Inputs!$B$29:$D$29) -> 4451.1719 | T8: =O8-Q8-R8-S8 -> -10166.005 | U8: =T8/D8 -> -0.011921185
A10: Tier 1 · launch | B10: DK | C10: =Inputs!$B$28 -> 56959 | D10: =Inputs!$B$29 -> 1029023.6 | E10: =D10/C10 -> 18.06604 | F10: =Inputs!$B$30 -> 115473.31 | G10: =Scenarios!$B$7 -> 0.25 | H10: =Scenarios!$C$7 -> 0.25 | I10: =D10*(G10+H10)/2 -> 257255.89 | J10: =Inputs!$B$31 -> 185586.06 | K10: =I10+F10-J10 -> 187143.14 | L10: =K10/D10 -> 0.18186478 | M10: =Inputs!$B$32 -> 99019.71 | N10: =Inputs!$B$8*D10/(Inputs!$B$29+Inputs!$C$29) -> 14297.19 | O10: =K10-M10 -> 88123.433 | P10: =O10/D10 -> 0.085637914 | Q10: =0 -> 0 | R10: =Inputs!$B$9*D10/(Inputs!$B$29+Inputs!$C$29) -> 14147.501 | S10: =Inputs!$B$11*D10/SUM(Inputs!$B$29:$D$29) -> 5371.1688 | T10: =O10-Q10-R10-S10 -> 68604.763 | U10: =T10/D10 -> 0.066669768
A11: Tier 1 · launch | B11: Resto | C11: =Inputs!$C$28 -> 1931 | D11: =Inputs!$C$29 -> 34036.47 | E11: =D11/C11 -> 17.626344 | F11: =Inputs!$C$30 -> 3810.16 | G11: =Scenarios!$D$7 -> 0.25 | H11: =Scenarios!$E$7 -> 0.25 | I11: =D11*(G11+H11)/2 -> 8509.1175 | J11: =Inputs!$C$31 -> 6495.05 | K11: =I11+F11-J11 -> 5824.2275 | L11: =K11/D11 -> 0.17111726 | M11: =Inputs!$C$32 -> 2001.89 | N11: =Inputs!$B$8*D11/(Inputs!$B$29+Inputs!$C$29) -> 120.98 | O11: =K11-M11 -> 3822.3375 | P11: =O11/D11 -> 0.11230123 | Q11: =0 -> 0 | R11: =Inputs!$B$9*D11/(Inputs!$B$29+Inputs!$C$29) -> 467.94942 | S11: =Inputs!$B$11*D11/SUM(Inputs!$B$29:$D$29) -> 177.65932 | T11: =O11-Q11-R11-S11 -> 3176.7288 | U11: =T11/D11 -> 0.093333086
A12: Tier 1 · launch | B12: Stores | C12: =Inputs!$D$28 -> 50400 | D12: =Inputs!$D$29 -> 852768 | E12: =D12/C12 -> 16.92 | F12: =Inputs!$D$30 -> 96768 | G12: =Scenarios!$F$7 -> 0.12 | H12: =Scenarios!$G$7 -> 0.12 | I12: =D12*(G12+H12)/2 -> 102332.16 | J12: =Inputs!$D$31 -> 171397.71 | K12: =I12+F12-J12 -> 27702.446 | L12: =K12/D12 -> 0.032485326 | M12: =Inputs!$D$32 -> 28728 | N12: =0 -> 0 | O12: =K12-M12 -> -1025.5536 | P12: =O12/D12 -> -0.0012026173 | Q12: =Inputs!$B$7 -> 28000 | R12: =Inputs!$B$10 -> 10800 | S12: =Inputs!$B$11*D12/SUM(Inputs!$B$29:$D$29) -> 4451.1719 | T12: =O12-Q12-R12-S12 -> -44276.725 | U12: =T12/D12 -> -0.051921185
A14: Tier 2 · €33k stores GMV / month | B14: DK | C14: =Inputs!$B$28 -> 56959 | D14: =Inputs!$B$29 -> 1029023.6 | E14: =D14/C14 -> 18.06604 | F14: =Inputs!$B$30 -> 115473.31 | G14: =Scenarios!$B$8 -> 0.25 | H14: =Scenarios!$C$8 -> 0.2 | I14: =D14*(G14+H14)/2 -> 231530.3 | J14: =Inputs!$B$31 -> 185586.06 | K14: =I14+F14-J14 -> 161417.55 | L14: =K14/D14 -> 0.15686478 | M14: =Inputs!$B$32 -> 99019.71 | N14: =Inputs!$B$8*D14/(Inputs!$B$29+Inputs!$C$29) -> 14297.19 | O14: =K14-M14 -> 62397.843 | P14: =O14/D14 -> 0.060637914 | Q14: =0 -> 0 | R14: =Inputs!$B$9*D14/(Inputs!$B$29+Inputs!$C$29) -> 14147.501 | S14: =Inputs!$B$11*D14/SUM(Inputs!$B$29:$D$29) -> 5371.1688 | T14: =O14-Q14-R14-S14 -> 42879.174 | U14: =T14/D14 -> 0.041669768
A15: Tier 2 · €33k stores GMV / month | B15: Resto | C15: =Inputs!$C$28 -> 1931 | D15: =Inputs!$C$29 -> 34036.47 | E15: =D15/C15 -> 17.626344 | F15: =Inputs!$C$30 -> 3810.16 | G15: =Scenarios!$D$8 -> 0.25 | H15: =Scenarios!$E$8 -> 0.2 | I15: =D15*(G15+H15)/2 -> 7658.2058 | J15: =Inputs!$C$31 -> 6495.05 | K15: =I15+F15-J15 -> 4973.3157 | L15: =K15/D15 -> 0.14611726 | M15: =Inputs!$C$32 -> 2001.89 | N15: =Inputs!$B$8*D15/(Inputs!$B$29+Inputs!$C$29) -> 120.98 | O15: =K15-M15 -> 2971.4257 | P15: =O15/D15 -> 0.087301232 | Q15: =0 -> 0 | R15: =Inputs!$B$9*D15/(Inputs!$B$29+Inputs!$C$29) -> 467.94942 | S15: =Inputs!$B$11*D15/SUM(Inputs!$B$29:$D$29) -> 177.65932 | T15: =O15-Q15-R15-S15 -> 2325.817 | U15: =T15/D15 -> 0.068333086
A16: Tier 2 · €33k stores GMV / month | B16: Stores | C16: =Inputs!$D$28 -> 50400 | D16: =Inputs!$D$29 -> 852768 | E16: =D16/C16 -> 16.92 | F16: =Inputs!$D$30 -> 96768 | G16: =Scenarios!$F$8 -> 0.12 | H16: =Scenarios!$G$8 -> 0.12 | I16: =D16*(G16+H16)/2 -> 102332.16 | J16: =Inputs!$D$31 -> 171397.71 | K16: =I16+F16-J16 -> 27702.446 | L16: =K16/D16 -> 0.032485326 | M16: =Inputs!$D$32 -> 28728 | N16: =0 -> 0 | O16: =K16-M16 -> -1025.5536 | P16: =O16/D16 -> -0.0012026173 | Q16: =Inputs!$B$7 -> 28000 | R16: =Inputs!$B$10 -> 10800 | S16: =Inputs!$B$11*D16/SUM(Inputs!$B$29:$D$29) -> 4451.1719 | T16: =O16-Q16-R16-S16 -> -44276.725 | U16: =T16/D16 -> -0.051921185
A18: Tier 3a · step-down to 16% | B18: DK | C18: =Inputs!$B$28 -> 56959 | D18: =Inputs!$B$29 -> 1029023.6 | E18: =D18/C18 -> 18.06604 | F18: =Inputs!$B$30 -> 115473.31 | G18: =Scenarios!$B$9 -> 0.2 | H18: =Scenarios!$C$9 -> 0.16 | I18: =D18*(G18+H18)/2 -> 185224.24 | J18: =Inputs!$B$31 -> 185586.06 | K18: =I18+F18-J18 -> 115111.49 | L18: =K18/D18 -> 0.11186478 | M18: =Inputs!$B$32 -> 99019.71 | N18: =Inputs!$B$8*D18/(Inputs!$B$29+Inputs!$C$29) -> 14297.19 | O18: =K18-M18 -> 16091.783 | P18: =O18/D18 -> 0.015637914 | Q18: =0 -> 0 | R18: =Inputs!$B$9*D18/(Inputs!$B$29+Inputs!$C$29) -> 14147.501 | S18: =Inputs!$B$11*D18/SUM(Inputs!$B$29:$D$29) -> 5371.1688 | T18: =O18-Q18-R18-S18 -> -3426.8867 | U18: =T18/D18 -> -0.0033302315
A19: Tier 3a · step-down to 16% | B19: Resto | C19: =Inputs!$C$28 -> 1931 | D19: =Inputs!$C$29 -> 34036.47 | E19: =D19/C19 -> 17.626344 | F19: =Inputs!$C$30 -> 3810.16 | G19: =Scenarios!$D$9 -> 0.2 | H19: =Scenarios!$E$9 -> 0.16 | I19: =D19*(G19+H19)/2 -> 6126.5646 | J19: =Inputs!$C$31 -> 6495.05 | K19: =I19+F19-J19 -> 3441.6746 | L19: =K19/D19 -> 0.10111726 | M19: =Inputs!$C$32 -> 2001.89 | N19: =Inputs!$B$8*D19/(Inputs!$B$29+Inputs!$C$29) -> 120.98 | O19: =K19-M19 -> 1439.7846 | P19: =O19/D19 -> 0.042301232 | Q19: =0 -> 0 | R19: =Inputs!$B$9*D19/(Inputs!$B$29+Inputs!$C$29) -> 467.94942 | S19: =Inputs!$B$11*D19/SUM(Inputs!$B$29:$D$29) -> 177.65932 | T19: =O19-Q19-R19-S19 -> 794.17587 | U19: =T19/D19 -> 0.023333086
A20: Tier 3a · step-down to 16% | B20: Stores | C20: =Inputs!$D$28 -> 50400 | D20: =Inputs!$D$29 -> 852768 | E20: =D20/C20 -> 16.92 | F20: =Inputs!$D$30 -> 96768 | G20: =Scenarios!$F$9 -> 0.12 | H20: =Scenarios!$G$9 -> 0.12 | I20: =D20*(G20+H20)/2 -> 102332.16 | J20: =Inputs!$D$31 -> 171397.71 | K20: =I20+F20-J20 -> 27702.446 | L20: =K20/D20 -> 0.032485326 | M20: =Inputs!$D$32 -> 28728 | N20: =0 -> 0 | O20: =K20-M20 -> -1025.5536 | P20: =O20/D20 -> -0.0012026173 | Q20: =Inputs!$B$7 -> 28000 | R20: =Inputs!$B$10 -> 10800 | S20: =Inputs!$B$11*D20/SUM(Inputs!$B$29:$D$29) -> 4451.1719 | T20: =O20-Q20-R20-S20 -> -44276.725 | U20: =T20/D20 -> -0.051921185
A22: Tier 3a · 12m DK/resto 16% | B22: DK | C22: =Inputs!$B$28 -> 56959 | D22: =Inputs!$B$29 -> 1029023.6 | E22: =D22/C22 -> 18.06604 | F22: =Inputs!$B$30 -> 115473.31 | G22: =Scenarios!$B$10 -> 0.16 | H22: =Scenarios!$C$10 -> 0.16 | I22: =D22*(G22+H22)/2 -> 164643.77 | J22: =Inputs!$B$31 -> 185586.06 | K22: =I22+F22-J22 -> 94531.021 | L22: =K22/D22 -> 0.091864777 | M22: =Inputs!$B$32 -> 99019.71 | N22: =Inputs!$B$8*D22/(Inputs!$B$29+Inputs!$C$29) -> 14297.19 | O22: =K22-M22 -> -4488.6888 | P22: =O22/D22 -> -0.0043620855 | Q22: =0 -> 0 | R22: =Inputs!$B$9*D22/(Inputs!$B$29+Inputs!$C$29) -> 14147.501 | S22: =Inputs!$B$11*D22/SUM(Inputs!$B$29:$D$29) -> 5371.1688 | T22: =O22-Q22-R22-S22 -> -24007.358 | U22: =T22/D22 -> -0.023330232
A23: Tier 3a · 12m DK/resto 16% | B23: Resto | C23: =Inputs!$C$28 -> 1931 | D23: =Inputs!$C$29 -> 34036.47 | E23: =D23/C23 -> 17.626344 | F23: =Inputs!$C$30 -> 3810.16 | G23: =Scenarios!$D$10 -> 0.16 | H23: =Scenarios!$E$10 -> 0.16 | I23: =D23*(G23+H23)/2 -> 5445.8352 | J23: =Inputs!$C$31 -> 6495.05 | K23: =I23+F23-J23 -> 2760.9452 | L23: =K23/D23 -> 0.08111726 | M23: =Inputs!$C$32 -> 2001.89 | N23: =Inputs!$B$8*D23/(Inputs!$B$29+Inputs!$C$29) -> 120.98 | O23: =K23-M23 -> 759.0552 | P23: =O23/D23 -> 0.022301232 | Q23: =0 -> 0 | R23: =Inputs!$B$9*D23/(Inputs!$B$29+Inputs!$C$29) -> 467.94942 | S23: =Inputs!$B$11*D23/SUM(Inputs!$B$29:$D$29) -> 177.65932 | T23: =O23-Q23-R23-S23 -> 113.44647 | U23: =T23/D23 -> 0.0033330856
A24: Tier 3a · 12m DK/resto 16% | B24: Stores | C24: =Inputs!$D$28 -> 50400 | D24: =Inputs!$D$29 -> 852768 | E24: =D24/C24 -> 16.92 | F24: =Inputs!$D$30 -> 96768 | G24: =Scenarios!$F$10 -> 0.12 | H24: =Scenarios!$G$10 -> 0.12 | I24: =D24*(G24+H24)/2 -> 102332.16 | J24: =Inputs!$D$31 -> 171397.71 | K24: =I24+F24-J24 -> 27702.446 | L24: =K24/D24 -> 0.032485326 | M24: =Inputs!$D$32 -> 28728 | N24: =0 -> 0 | O24: =K24-M24 -> -1025.5536 | P24: =O24/D24 -> -0.0012026173 | Q24: =Inputs!$B$7 -> 28000 | R24: =Inputs!$B$10 -> 10800 | S24: =Inputs!$B$11*D24/SUM(Inputs!$B$29:$D$29) -> 4451.1719 | T24: =O24-Q24-R24-S24 -> -44276.725 | U24: =T24/D24 -> -0.051921185
A26: Tier 3b · step to shared 16% | B26: DK | C26: =Inputs!$B$28 -> 56959 | D26: =Inputs!$B$29 -> 1029023.6 | E26: =D26/C26 -> 18.06604 | F26: =Inputs!$B$30 -> 115473.31 | G26: =Scenarios!$B$11 -> 0.2 | H26: =Scenarios!$C$11 -> 0.16 | I26: =D26*(G26+H26)/2 -> 185224.24 | J26: =Inputs!$B$31 -> 185586.06 | K26: =I26+F26-J26 -> 115111.49 | L26: =K26/D26 -> 0.11186478 | M26: =Inputs!$B$32 -> 99019.71 | N26: =Inputs!$B$8*D26/(Inputs!$B$29+Inputs!$C$29) -> 14297.19 | O26: =K26-M26 -> 16091.783 | P26: =O26/D26 -> 0.015637914 | Q26: =0 -> 0 | R26: =Inputs!$B$9*D26/(Inputs!$B$29+Inputs!$C$29) -> 14147.501 | S26: =Inputs!$B$11*D26/SUM(Inputs!$B$29:$D$29) -> 5371.1688 | T26: =O26-Q26-R26-S26 -> -3426.8867 | U26: =T26/D26 -> -0.0033302315
A27: Tier 3b · step to shared 16% | B27: Resto | C27: =Inputs!$C$28 -> 1931 | D27: =Inputs!$C$29 -> 34036.47 | E27: =D27/C27 -> 17.626344 | F27: =Inputs!$C$30 -> 3810.16 | G27: =Scenarios!$D$11 -> 0.2 | H27: =Scenarios!$E$11 -> 0.16 | I27: =D27*(G27+H27)/2 -> 6126.5646 | J27: =Inputs!$C$31 -> 6495.05 | K27: =I27+F27-J27 -> 3441.6746 | L27: =K27/D27 -> 0.10111726 | M27: =Inputs!$C$32 -> 2001.89 | N27: =Inputs!$B$8*D27/(Inputs!$B$29+Inputs!$C$29) -> 120.98 | O27: =K27-M27 -> 1439.7846 | P27: =O27/D27 -> 0.042301232 | Q27: =0 -> 0 | R27: =Inputs!$B$9*D27/(Inputs!$B$29+Inputs!$C$29) -> 467.94942 | S27: =Inputs!$B$11*D27/SUM(Inputs!$B$29:$D$29) -> 177.65932 | T27: =O27-Q27-R27-S27 -> 794.17587 | U27: =T27/D27 -> 0.023333086
A28: Tier 3b · step to shared 16% | B28: Stores | C28: =Inputs!$D$28 -> 50400 | D28: =Inputs!$D$29 -> 852768 | E28: =D28/C28 -> 16.92 | F28: =Inputs!$D$30 -> 96768 | G28: =Scenarios!$F$11 -> 0.12 | H28: =Scenarios!$G$11 -> 0.16 | I28: =D28*(G28+H28)/2 -> 119387.52 | J28: =Inputs!$D$31 -> 171397.71 | K28: =I28+F28-J28 -> 44757.806 | L28: =K28/D28 -> 0.052485326 | M28: =Inputs!$D$32 -> 28728 | N28: =0 -> 0 | O28: =K28-M28 -> 16029.806 | P28: =O28/D28 -> 0.018797383 | Q28: =Inputs!$B$7 -> 28000 | R28: =Inputs!$B$10 -> 10800 | S28: =Inputs!$B$11*D28/SUM(Inputs!$B$29:$D$29) -> 4451.1719 | T28: =O28-Q28-R28-S28 -> -27221.365 | U28: =T28/D28 -> -0.031921185
A30: Tier 3b · 12m shared 16% | B30: DK | C30: =Inputs!$B$28 -> 56959 | D30: =Inputs!$B$29 -> 1029023.6 | E30: =D30/C30 -> 18.06604 | F30: =Inputs!$B$30 -> 115473.31 | G30: =Scenarios!$B$12 -> 0.16 | H30: =Scenarios!$C$12 -> 0.16 | I30: =D30*(G30+H30)/2 -> 164643.77 | J30: =Inputs!$B$31 -> 185586.06 | K30: =I30+F30-J30 -> 94531.021 | L30: =K30/D30 -> 0.091864777 | M30: =Inputs!$B$32 -> 99019.71 | N30: =Inputs!$B$8*D30/(Inputs!$B$29+Inputs!$C$29) -> 14297.19 | O30: =K30-M30 -> -4488.6888 | P30: =O30/D30 -> -0.0043620855 | Q30: =0 -> 0 | R30: =Inputs!$B$9*D30/(Inputs!$B$29+Inputs!$C$29) -> 14147.501 | S30: =Inputs!$B$11*D30/SUM(Inputs!$B$29:$D$29) -> 5371.1688 | T30: =O30-Q30-R30-S30 -> -24007.358 | U30: =T30/D30 -> -0.023330232
A31: Tier 3b · 12m shared 16% | B31: Resto | C31: =Inputs!$C$28 -> 1931 | D31: =Inputs!$C$29 -> 34036.47 | E31: =D31/C31 -> 17.626344 | F31: =Inputs!$C$30 -> 3810.16 | G31: =Scenarios!$D$12 -> 0.16 | H31: =Scenarios!$E$12 -> 0.16 | I31: =D31*(G31+H31)/2 -> 5445.8352 | J31: =Inputs!$C$31 -> 6495.05 | K31: =I31+F31-J31 -> 2760.9452 | L31: =K31/D31 -> 0.08111726 | M31: =Inputs!$C$32 -> 2001.89 | N31: =Inputs!$B$8*D31/(Inputs!$B$29+Inputs!$C$29) -> 120.98 | O31: =K31-M31 -> 759.0552 | P31: =O31/D31 -> 0.022301232 | Q31: =0 -> 0 | R31: =Inputs!$B$9*D31/(Inputs!$B$29+Inputs!$C$29) -> 467.94942 | S31: =Inputs!$B$11*D31/SUM(Inputs!$B$29:$D$29) -> 177.65932 | T31: =O31-Q31-R31-S31 -> 113.44647 | U31: =T31/D31 -> 0.0033330856
A32: Tier 3b · 12m shared 16% | B32: Stores | C32: =Inputs!$D$28 -> 50400 | D32: =Inputs!$D$29 -> 852768 | E32: =D32/C32 -> 16.92 | F32: =Inputs!$D$30 -> 96768 | G32: =Scenarios!$F$12 -> 0.16 | H32: =Scenarios!$G$12 -> 0.16 | I32: =D32*(G32+H32)/2 -> 136442.88 | J32: =Inputs!$D$31 -> 171397.71 | K32: =I32+F32-J32 -> 61813.166 | L32: =K32/D32 -> 0.072485326 | M32: =Inputs!$D$32 -> 28728 | N32: =0 -> 0 | O32: =K32-M32 -> 33085.166 | P32: =O32/D32 -> 0.038797383 | Q32: =Inputs!$B$7 -> 28000 | R32: =Inputs!$B$10 -> 10800 | S32: =Inputs!$B$11*D32/SUM(Inputs!$B$29:$D$29) -> 4451.1719 | T32: =O32-Q32-R32-S32 -> -10166.005 | U32: =T32/D32 -> -0.011921185

Sheet Source & assumptions
A1: Source data and calculation assumptions
A4: Source | B4: Metric / assumption | C4: Value | D4: Treatment | E4: Notes | F4: Status
A5: Silpo 2027 — DK & Resto profitability calculator.xlsx | B5: Historical DK + resto | C5: Oct-2025–Sep-2026 | D5: Pulled into Inputs | E5: DK_A + DK_B + Resto | F5: Used
A6: SILPO business model (6).xlsx | B6: Stores scenario | C6: Shared rate 16% | D6: Pulled into Inputs | E6: Column L | F6: Used
A7: Eater fees | B7: DK/resto | C7: €119.3k | D7: Displayed separately | E7: Already contained in historical CP unit economics | F7: Informational
A8: DF campaign | B8: DK/resto | C8: €14.4k | D8: Inside historical DI | E8: Visible but not deducted a second time | F8: Informational
A9: DF campaign | B9: Stores | C9: €28.0k | D9: Incremental cash cost | E9: 6 of 12 months | F9: Editable
A10: Bolt+ | B10: All verticals | C10: €25.4k | D10: Incremental cash cost | E10: Delivery base only; no SF/SOF discount | F10: Editable
